enferno_cli/__init__.py
enferno_cli/__main__.py
enferno_cli/cli.py
enferno_cli/core/__init__.py
enferno_cli/core/config.py
enferno_cli/core/manager.py
enferno_cli/core/ssh.py
enferno_cli/core/task.py
enferno_cli/core/templates.py
enferno_cli/tasks/__init__.py
enferno_cli/tasks/database.py
enferno_cli/tasks/enferno.py
enferno_cli/tasks/firewall.py
enferno_cli/tasks/nginx.py
enferno_cli/tasks/packages.py
enferno_cli/tasks/python.py
enferno_cli/tasks/service.py
enferno_cli/tasks/user.py
enferno_cli/templates/__init__.py
enferno_cli/templates/basic.conf
enferno_cli/templates/clry.service
enferno_cli/templates/default.conf
enferno_cli/templates/enferno.env
enferno_cli/templates/enferno.service
enferno_cli/templates/initial-ssl.conf
enferno_cli/templates/nginx.conf.j2
enferno_cli/templates/ssl.conf
enferno_cli/utils/__init__.py
enferno_cli-0.2.0.dist-info/entry_points.txt
enferno_cli-0.2.0.dist-info/LICENSE
enferno_cli-0.2.0.dist-info/WHEEL
enferno_cli-0.2.0.dist-info/METADATA
enferno_cli-0.2.0.dist-info/RECORD
