Metadata-Version: 2.1
Name: enferno_cli
Version: 0.2.0
Summary: A Python tool for setting up Ubuntu servers with the Enferno framework
Author-email: Nidal Alhariri <level09@gmail.com>
Requires-Python: >=3.9
Classifier: Development Status :: 3 - Alpha
Classifier: Intended Audience :: Developers
Classifier: Intended Audience :: System Administrators
Classifier: License :: OSI Approved :: MIT License
Classifier: Programming Language :: Python :: 3
Classifier: Programming Language :: Python :: 3.9
Classifier: Programming Language :: Python :: 3.10
Classifier: Programming Language :: Python :: 3.11
Classifier: Programming Language :: Python :: 3.12
Classifier: Programming Language :: Python :: 3.13
Classifier: Topic :: System :: Installation/Setup
Classifier: Topic :: System :: Systems Administration
Requires-Dist: click>=8.0.0
Requires-Dist: paramiko>=2.7.0
Requires-Dist: python-dotenv>=0.19.0
Requires-Dist: jinja2>=3.0.0
Requires-Dist: pyyaml>=6.0
Requires-Dist: rich>=10.0.0
Requires-Dist: black>=22.3.0 ; extra == "dev"
Requires-Dist: isort>=5.10.1 ; extra == "dev"
Requires-Dist: flake8>=4.0.1 ; extra == "dev"
Requires-Dist: mypy>=0.950 ; extra == "dev"
Project-URL: Documentation, https://github.com/level09/enferno-cli#readme
Project-URL: Home, https://github.com/level09/enferno-cli
Project-URL: Issues, https://github.com/level09/enferno-cli/issues
Project-URL: Source, https://github.com/level09/enferno-cli
Provides-Extra: dev
